multispecqr/__about__.py
multispecqr/__init__.py
multispecqr/__main__.py
multispecqr/_cli.py
multispecqr/calibration.py
multispecqr/decoder.py
multispecqr/encoder.py
multispecqr/ml_decoder.py
multispecqr/palette.py
multispecqr-0.4.1.dist-info/LICENSE.txt
multispecqr-0.4.1.dist-info/METADATA
multispecqr-0.4.1.dist-info/WHEEL
multispecqr-0.4.1.dist-info/entry_points.txt
multispecqr-0.4.1.dist-info/RECORD
