Metadata-Version: 2.1
Name: multispecqr
Version: 0.4.1
Summary: Encode and decode multi-spectral / multi-layer QR codes (RGB, UV, NIR) with optional ML-based separation.
License: MIT
Keywords: qr,multispectral,barcode
Author: Muntaser Syed
Author-email: jemsbhai@gmail.com
Requires-Python: >=3.9,<3.13
Classifier: Development Status :: 4 - Beta
Classifier: License :: OSI Approved :: MIT License
Classifier: Programming Language :: Python
Classifier: Programming Language :: Python :: 3
Classifier: Programming Language :: Python :: 3.9
Classifier: Programming Language :: Python :: 3.10
Classifier: Programming Language :: Python :: 3.11
Classifier: Programming Language :: Python :: 3.12
Classifier: Programming Language :: Python :: Implementation :: CPython
Requires-Dist: numpy (>=1.20)
Requires-Dist: opencv-python (>=4.0)
Requires-Dist: pillow (>=9.0)
Requires-Dist: pyzbar (>=0.1.9)
Requires-Dist: qrcode[pil] (>=7.0)
Requires-Dist: scikit-learn (>=1.0)
Project-URL: Documentation, https://github.com/jemsbhai/multispecqr#readme
Project-URL: Issues, https://github.com/jemsbhai/multispecqr/issues
Project-URL: Source, https://github.com/jemsbhai/multispecqr
